diskit/__init__.py
diskit/circuit_remapper.py
diskit/components/__init__.py
diskit/components/layer.py
diskit/components/topology.py
diskit-0.0.1.post2.dist-info/LICENSE
diskit-0.0.1.post2.dist-info/METADATA
diskit-0.0.1.post2.dist-info/WHEEL
diskit-0.0.1.post2.dist-info/top_level.txt
diskit-0.0.1.post2.dist-info/RECORD
