Metadata-Version: 2.1
Name: diskit
Version: 0.0.1.post2
Summary: Distributed circuit remapping for Qiskit
Home-page: https://github.com/Interlin-q/diskit
Author: Anuranan Das, Stephen DiAdamo
Author-email: stephen.diadamo@gmail.com
License: Apache
Keywords: quantum,distributed,simulator,qiskit,diskit
Classifier: Programming Language :: Python :: 3
Classifier: License :: OSI Approved :: Apache Software License
Classifier: Operating System :: OS Independent
Requires-Python: >=3.6
License-File: LICENSE
Requires-Dist: qiskit
